ssmpm/__init__.py
ssmpm-1.0.6.data/scripts/ssmpm
ssmpm-1.0.6.dist-info/LICENSE
ssmpm-1.0.6.dist-info/METADATA
ssmpm-1.0.6.dist-info/WHEEL
ssmpm-1.0.6.dist-info/top_level.txt
ssmpm-1.0.6.dist-info/RECORD
