Metadata-Version: 2.1
Name: ssmpm
Version: 1.0.6
Summary: SSM Parameter Manager
Home-page: https://github.com/craighurley/ssmpm
Author: Craig Hurley
Author-email: craighurley78@gmail.com
License: MIT
Keywords: ssm,parameter,aws
Platform: UNKNOWN
Classifier: Intended Audience :: Developers
Classifier: Natural Language :: English
Classifier: Environment :: Console
Classifier: Programming Language :: Python :: 3
Classifier: License :: OSI Approved :: MIT License
Requires-Python: >=3.8
Requires-Dist: boto3 (>=1.14.0)
Requires-Dist: docopt (>=0.6.2)
Requires-Dist: termcolor (>=1.1.0)
